README.md
setup.cfg
setup.py
spotcrime/__init__.py
spotcrime.egg-info/PKG-INFO
spotcrime.egg-info/SOURCES.txt
spotcrime.egg-info/dependency_links.txt
spotcrime.egg-info/requires.txt
spotcrime.egg-info/top_level.txt