Metadata-Version: 1.1
Name: spotcrime
Version: 1.0.4
Summary: Provides basic API to spotcrime.com.
Home-page: https://github.com/jcconnell/python-spotcrime
Author: jcconnell
Author-email: jamescarltonconnell@gmail.com
License: MIT
Platform: UNKNOWN
Classifier: License :: OSI Approved :: MIT License
Classifier: Operating System :: OS Independent
Classifier: Programming Language :: Python :: 3
